Workbook
Name aporte: Planilha1!$E$8
Name patrimonio: Planilha1!$E$11
Name qtd_anos: Planilha1!$E$9
Name rendimento_carteira: Planilha1!$J$9
Name salario: Planilha1!$J$8
Name sugestao_investimento: Planilha1!$J$10
Name taxa_mensal: Planilha1!$E$10

Sheet Planilha1
B7: INVESTIMENTO MENSAL | G7: CONFIGURAÇÕES
B8: Quanto investir por mês? | E8: 500 | G8: Salário | J8: 6700
B9: Por quantos anos? | E9: 5 | G9: Rendimento Carteira | J9: 0.009
B10: Taxa de rendimento mensal? | E10: 0.0108 | G10: Sugestão de Investimento | J10: =J8*30% -> 2010
B11: Patrimônio acumulado? | E11: =FV(taxa_mensal,qtd_anos*12,aporte*-1) -> 41902.01
B12: Dividendos mensais? | E12: =patrimonio*rendimento_carteira -> 377.11809
B14: CENÁRIOS | F14: Dividendo
B15: Quanto em 2 anos? | E15: =FV($E$10,2*12,$E$8*-1) -> 13615.432 | F15: =E15*rendimento_carteira -> 122.53889
B16: Quanto em 5 anos? | E16: =FV($E$10,5*12,$E$8*-1) -> 41902.01 | F16: =E16*rendimento_carteira -> 377.11809
B17: Quanto em 10 anos? | E17: =FV($E$10,10*12,$E$8*-1) -> 121728.83 | F17: =E17*rendimento_carteira -> 1095.5595
B18: Quanto em 20 anos? | E18: =FV($E$10,20*12,$E$8*-1) -> 563524.5 | F18: =E18*rendimento_carteira -> 5071.7205
B19: Quanto em 30 anos? | E19: =FV($E$10,30*12,$E$8*-1) -> 2166952.4 | F19: =E19*rendimento_carteira -> 19502.572
B23: Perfil | F23: Agressivo
B24: VALOR A SER INVESTIDO POR MÊS | F24: =aporte -> 500
B26: TIPO DE FII | D26: PERCENTUAL SUGERIDO | F26: VALORES
B27: PAPEL | D27: =VLOOKUP($F$23&" - "&B27,Planilha2!$A:$E,5,) -> 0.5 | F27: =D27*$F$24 -> 250
B28: TIJOLO | D28: =VLOOKUP($F$23&" - "&B28,Planilha2!$A:$E,5,) -> 0.1 | F28: =D28*$F$24 -> 50
B29: HÍBRIDO | D29: =VLOOKUP($F$23&" - "&B29,Planilha2!$A:$E,5,) -> 0.05 | F29: =D29*$F$24 -> 25
B30: FOFs | D30: =VLOOKUP($F$23&" - "&B30,Planilha2!$A:$E,5,) -> 0.05 | F30: =D30*$F$24 -> 25
B31: DESENVOLVIMENTO | D31: =VLOOKUP($F$23&" - "&B31,Planilha2!$A:$E,5,) -> 0.2 | F31: =D31*$F$24 -> 100
B32: HOTELARIAS | D32: =VLOOKUP($F$23&" - "&B32,Planilha2!$A:$E,5,) -> 0.1 | F32: =D32*$F$24 -> 50
F33: =SUM(F27:F32) -> 500

Sheet Planilha2
A2: CHAVE | B2: PERFIL | C2: TIPO DE FII | E2: %
A3: =B3&" - "&C3 -> Conservador - PAPEL | B3: Conservador | C3: PAPEL | E3: 0.3
A4: =B4&" - "&C4 -> Conservador - TIJOLO | B4: Conservador | C4: TIJOLO | E4: 0.5
A5: =B5&" - "&C5 -> Conservador - HÍBRIDO | B5: Conservador | C5: HÍBRIDO | E5: 0.1
A6: =B6&" - "&C6 -> Conservador - FOFs | B6: Conservador | C6: FOFs | E6: 0.1
A7: =B7&" - "&C7 -> Conservador - DESENVOLVIMENTO | B7: Conservador | C7: DESENVOLVIMENTO | E7: 0
A8: =B8&" - "&C8 -> Conservador - HOTELARIAS | B8: Conservador | C8: HOTELARIAS | E8: 0
A9: =B9&" - "&C9 -> Moderado - PAPEL | B9: Moderado | C9: PAPEL | E9: 0.32
A10: =B10&" - "&C10 -> Moderado - TIJOLO | B10: Moderado | C10: TIJOLO | E10: 0.35
A11: =B11&" - "&C11 -> Moderado - HÍBRIDO | B11: Moderado | C11: HÍBRIDO | E11: 0.08
A12: =B12&" - "&C12 -> Moderado - FOFs | B12: Moderado | C12: FOFs | E12: 0.05
A13: =B13&" - "&C13 -> Moderado - DESENVOLVIMENTO | B13: Moderado | C13: DESENVOLVIMENTO | E13: 0.1
A14: =B14&" - "&C14 -> Moderado - HOTELARIAS | B14: Moderado | C14: HOTELARIAS | E14: 0.1
... A20: =B20&" - "&C20 -> Agressivo - HOTELARIAS | B20: Agressivo | C20: HOTELARIAS | E20: 0.1
